bing_image_downloader/__init__.py
bing_image_downloader/bing.py
bing_image_downloader/downloader.py
bing_image_downloader_ext-1.1.6.dist-info/LICENSE
bing_image_downloader_ext-1.1.6.dist-info/METADATA
bing_image_downloader_ext-1.1.6.dist-info/WHEEL
bing_image_downloader_ext-1.1.6.dist-info/top_level.txt
bing_image_downloader_ext-1.1.6.dist-info/RECORD
