Metadata-Version: 2.1
Name: bing_image_downloader_ext
Version: 1.1.6
Summary: Forked version of bing_image_downloader with support for resizing, file types, and size filters
Home-page: https://github.com/loglux/bing_image_downloader
Author: Loglux
Author-email: 
Keywords: bing,images,scraping,image download,bulk image downloader,resize,file type,size filter
Classifier: Programming Language :: Python :: 3
Classifier: License :: OSI Approved :: MIT License
Classifier: Operating System :: OS Independent
License-File: LICENSE
Requires-Dist: Pillow
